{"type":"Feature","stac_version":"1.0.0","stac_extensions":["https://stac-extensions.github.io/projection/v1.1.0/schema.json","https://stac-extensions.github.io/raster/v1.1.0/schema.json"],"id":"USGS_1M_13_x27y429_CO_WestCentral_2019_A19","geometry":{"type":"Polygon","coordinates":[[[-107.64261406521209,38.638670493862875],[-107.52768919891403,38.641211670879215],[-107.53086453594956,38.73135012066026],[-107.64593337178542,38.72880078942527],[-107.64261406521209,38.638670493862875]]]},"bbox":[-107.64593337178542,38.638670493862875,-107.52768919891403,38.73135012066026],"properties":{"start_datetime":"2019-08-21T00:00:00Z","end_datetime":"2019-09-19T00:00:00Z","proj:epsg":null,"proj:geometry":{"type":"Polygon","coordinates":[[[269994.0000102301,4279994.0000072755],[280006.0000102301,4279994.0000072755],[280006.0000102301,4290006.0000072755],[269994.0000102301,4290006.0000072755],[269994.0000102301,4279994.0000072755]]]},"proj:bbox":[269994.0000102301,4279994.0000072755,280006.0000102301,4290006.0000072755],"proj:shape":[10012,10012],"proj:transform":[1.0,0.0,269994.0000102301,0.0,-1.0,4290006.0000072755,0.0,0.0,1.0],"proj:projjson":{"$schema":"https://proj.org/schemas/v0.7/projjson.schema.json","type":"ProjectedCRS","name":"NAD83 / UTM zone 13N","base_crs":{"name":"NAD83","datum":{"type":"GeodeticReferenceFrame","name":"North American Datum 1983","ellipsoid":{"name":"GRS 1980","semi_major_axis":6378137,"inverse_flattening":298.257222101}},"coordinate_system":{"subtype":"ellipsoidal","axis":[{"name":"Geodetic latitude","abbreviation":"Lat","direction":"north","unit":"degree"},{"name":"Geodetic longitude","abbreviation":"Lon","direction":"east","unit":"degree"}]},"id":{"authority":"EPSG","code":4269}},"conversion":{"name":"UTM zone 13N","method":{"name":"Transverse Mercator","id":{"authority":"EPSG","code":9807}},"parameters":[{"name":"Latitude of natural origin","value":0,"unit":"degree","id":{"authority":"EPSG","code":8801}},{"name":"Longitude of natural origin","value":-105,"unit":"degree","id":{"authority":"EPSG","code":8802}},{"name":"Scale factor at natural origin","value":0.9996,"unit":"unity","id":{"authority":"EPSG","code":8805}},{"name":"False easting","value":500000,"unit":"metre","id":{"authority":"EPSG","code":8806}},{"name":"False northing","value":0,"unit":"metre","id":{"authority":"EPSG","code":8807}}]},"coordinate_system":{"subtype":"Cartesian","axis":[{"name":"Easting","abbreviation":"","direction":"east","unit":"metre"},{"name":"Northing","abbreviation":"","direction":"north","unit":"metre"}]},"id":{"authority":"EPSG","code":26913}},"datetime":null},"links":[{"rel":"collection","href":"CO_WestCentral_2019_A19","type":"application/json"}],"assets":{"image":{"href":"https://prd-tnm.s3.amazonaws.com/StagedProducts/Elevation/1m/Projects/CO_WestCentral_2019_A19/TIFF/USGS_1M_13_x27y429_CO_WestCentral_2019_A19.tif","type":"image/tiff; application=geotiff","raster:bands":[{"data_type":"float32","scale":1.0,"offset":0.0,"sampling":"area","nodata":-999999.0,"statistics":{"mean":2115.135377216254,"minimum":1886.248046875,"maximum":2716.620849609375,"stddev":104.45716516238767,"valid_percent":87.60557174682617},"histogram":{"count":11,"min":1886.248046875,"max":2716.620849609375,"buckets":[27128,249550,324229,174050,85586,42334,10729,2527,1687,791]}}],"roles":["data"]}},"collection":"CO_WestCentral_2019_A19"}